skeleton/__init__.py
wils/__init__.py
wils-0.1.1.dist-info/LICENSE
wils-0.1.1.dist-info/METADATA
wils-0.1.1.dist-info/WHEEL
wils-0.1.1.dist-info/top_level.txt
wils-0.1.1.dist-info/RECORD
