Metadata-Version: 2.1
Name: wils
Version: 0.1.1
Summary: Utils used by wbswjc himself
Home-page: https://github.com/wbswjc/wils
Author: wbswjc
Author-email: me@wbswjc.com
License: MIT
Platform: UNKNOWN
Requires-Dist: wils (>=0.1.0)
